gravitational/__init__.py
gravitational/constants.py
gravitational/orbit.py
gravitational/plays.py
gravitational/simulation.py
gravitational/solar_system.py
gravitational/utils.py
gravitational-0.2.2.dist-info/LICENSE.txt
gravitational-0.2.2.dist-info/METADATA
gravitational-0.2.2.dist-info/WHEEL
gravitational-0.2.2.dist-info/top_level.txt
gravitational-0.2.2.dist-info/RECORD
