Metadata-Version: 2.1
Name: gravitational
Version: 0.2.2
Summary: A package for gravitational simulations
Home-page: https://github.com/behrouzz/gravitational
Author: Behrouz Safari
Author-email: behrouz.safari@gmail.com
License: MIT
Platform: UNKNOWN
Classifier: Programming Language :: Python :: 3
Classifier: License :: OSI Approved :: MIT License
Classifier: Operating System :: OS Independent
Requires-Python: >=3.6
